constantia/__init__.py
constantia/consts/__init__.py
constantia/consts/const_assignment_visitor.py
constantia/consts/decorator.py
constantia/consts/typing.py
constantia/tests/__init__.py
constantia/tests/decorators/__init__.py
constantia/tests/decorators/check_at_import/__init__.py
constantia/tests/decorators/check_at_import/test_consts_at_import.py
constantia/tests/decorators/check_at_import/cases/__init__.py
constantia/tests/decorators/check_at_import/cases/class_constants_cannot_be_reassigned.py
constantia/tests/decorators/check_at_import/cases/class_constants_cannot_be_reassigned_in_class_method.py
constantia/tests/decorators/check_at_import/cases/class_constants_cannot_be_reassigned_in_static_method.py
constantia/tests/decorators/check_at_import/cases/class_constants_ok.py
constantia/tests/decorators/check_at_import/cases/constants_cannot_be_mutable.py
constantia/tests/decorators/check_at_import/cases/constants_cannot_be_reassigned.py
constantia/tests/decorators/check_at_import/cases/ok.py
constantia/tests/decorators/check_at_runtime/__init__.py
constantia/tests/decorators/check_at_runtime/test_consts_at_runtime.py
constantia/tests/decorators/check_at_runtime/cases/__init__.py
constantia/tests/decorators/check_at_runtime/cases/class_constants_cannot_be_reassigned.py
constantia/tests/decorators/check_at_runtime/cases/class_constants_cannot_be_reassigned_in_class_method.py
constantia/tests/decorators/check_at_runtime/cases/class_constants_cannot_be_reassigned_in_static_method.py
constantia/tests/decorators/check_at_runtime/cases/class_constants_ok.py
constantia/tests/decorators/check_at_runtime/cases/constants_cannot_be_mutable.py
constantia/tests/decorators/check_at_runtime/cases/constants_cannot_be_reassigned.py
constantia/tests/decorators/check_at_runtime/cases/ok.py
constantia-0.0.1.dist-info/LICENSE
constantia-0.0.1.dist-info/METADATA
constantia-0.0.1.dist-info/WHEEL
constantia-0.0.1.dist-info/top_level.txt
constantia-0.0.1.dist-info/RECORD
