Metadata-Version: 2.2
Name: constantia
Version: 0.0.1
Summary: Enforce constants at import time
Home-page: https://github.com/diegojromerolopez/constantia
Author: Diego J. Romero López
Author-email: "Diego J. Romero López" <diegojromerolopez@gmail.com>
License: MIT
Project-URL: Homepage, https://github.com/diegojromerolopez/constantia
Project-URL: Issues, https://github.com/diegojromerolopez/constantia/issues
Classifier: Programming Language :: Python :: Implementation :: CPython
Classifier: Programming Language :: Python :: Implementation :: PyPy
Classifier: Programming Language :: Python :: 3.10
Classifier: Programming Language :: Python :: 3.11
Classifier: Programming Language :: Python :: 3.12
Classifier: Programming Language :: Python :: 3.13
Classifier: Topic :: Software Development :: Libraries
Classifier: Development Status :: 2 - Pre-Alpha
Classifier: License :: OSI Approved :: MIT License
Requires-Python: >=3.10
License-File: LICENSE
Dynamic: author
Dynamic: home-page
